Metadata-Version: 2.1
Name: ndc
Version: 1.0
Summary: Numerical differentiation leveraging convolutions based on PyTorch
Home-page: https://github.com/famura/ndc
Author: Fabio Muratore
Author-email: robo-learning@famura.net
License: UNKNOWN
Project-URL: Source, https://github.com/famura/ndc
Project-URL: Bug Reports, https://github.com/famura/ndc/issues
Keywords: numerical differentiation,finite differences,convolution,signal processing
Platform: UNKNOWN
Classifier: License :: OSI Approved :: MIT License
Classifier: Development Status :: 4 - Beta
Classifier: Operating System :: OS Independent
Classifier: Programming Language :: Python :: 3.10
Classifier: Programming Language :: Python :: 3.9
Classifier: Programming Language :: Python :: 3.8
Classifier: Programming Language :: Python :: 3.7
Classifier: Programming Language :: Python :: 3.6
Classifier: Programming Language :: Python :: 3 :: Only
Requires-Python: >=3.6, <4
Provides-Extra: dev
License-File: LICENSE.txt
